pypackagescraper/__init__.py
pypackagescraper-0.9.0.dist-info/METADATA
pypackagescraper-0.9.0.dist-info/WHEEL
pypackagescraper-0.9.0.dist-info/top_level.txt
pypackagescraper-0.9.0.dist-info/RECORD
