Metadata-Version: 2.1
Name: pypackagescraper
Version: 0.9.0
Summary: PyPackageScraper is a Python library designed to make it easy to gather information and data from other Python packages.
Author: Nick
Author-email: nescher@kekw.xyz
Keywords: python
Classifier: Operating System :: Microsoft :: Windows
